reg_monkey/__init__.py
reg_monkey/baseline_spec.py
reg_monkey/code_executor.py
reg_monkey/code_generator.py
reg_monkey/data_loader.py
reg_monkey/data_manager.py
reg_monkey/planner.py
reg_monkey/r_template.jinja
reg_monkey/task_obj.py
reg_monkey/util.py
regression_monkey-0.1.2.dist-info/licenses/LICENSE
regression_monkey-0.1.2.dist-info/METADATA
regression_monkey-0.1.2.dist-info/WHEEL
regression_monkey-0.1.2.dist-info/top_level.txt
regression_monkey-0.1.2.dist-info/RECORD
