Metadata-Version: 2.4
Name: regression_monkey
Version: 0.1.2
Summary: Reproducible regression workflow: loaders → dependency tracking → codegen → execution.
Author-email: Your Name <you@example.com>
License: MIT License
Project-URL: Homepage, https://example.com/regmonkey
Project-URL: Repository, https://example.com/regmonkey
Project-URL: Issues, https://example.com/regmonkey/issues
Keywords: econometrics,regression,reproducibility,rpy2,jinja2,arcticdb
Classifier: Development Status :: 3 - Alpha
Classifier: Intended Audience :: Science/Research
Classifier: License :: OSI Approved :: MIT License
Classifier: Programming Language :: Python
Classifier: Programming Language :: Python :: 3
Classifier: Programming Language :: Python :: 3 :: Only
Classifier: Programming Language :: Python :: 3.9
Classifier: Programming Language :: Python :: 3.10
Classifier: Programming Language :: Python :: 3.11
Classifier: Programming Language :: Python :: 3.12
Classifier: Topic :: Scientific/Engineering
Classifier: Topic :: Scientific/Engineering :: Information Analysis
Requires-Python: >=3.9
License-File: LICENSE
Requires-Dist: pandas>=2.0
Requires-Dist: numpy>=1.24
Requires-Dist: jinja2>=3.1
Requires-Dist: rpy2>=3.5; platform_system != "Windows"
Requires-Dist: pyyaml>=6.0
Requires-Dist: arcticdb>=6.2.3
Provides-Extra: dev
Requires-Dist: pytest>=7.0; extra == "dev"
Requires-Dist: black>=24.0; extra == "dev"
Requires-Dist: ruff>=0.5; extra == "dev"
Requires-Dist: build>=1.2.1; extra == "dev"
Requires-Dist: twine>=5.0; extra == "dev"
Provides-Extra: full
Requires-Dist: arcticdb>=4.5; extra == "full"
Dynamic: license-file
